<?xml version="1.0" ?>
<levelConfig gameName="BattleCity" version="1.0" levelIndex="1" name="Level 1">
    <level width="800" height="600" cols="40" rows="30">
        <players>
            <player id="player1" x="50" y="550"/>
            <player id="player2" x="770" y="550"/>
        </players>
        <enemies>
            <enemy id="enemy1_23" type="fastEnemy" x="470" y="30"/>
            <enemy id="enemy1_38" type="powerfulEnemy" x="770" y="30"/>
            <enemy id="enemy2_7" type="powerfulEnemy" x="150" y="50"/>
            <enemy id="enemy6_12" type="fastEnemy" x="250" y="130"/>
            <enemy id="enemy6_24" type="regularEnemy" x="490" y="130"/>
            <enemy id="enemy11_7" type="regularEnemy" x="150" y="230"/>
            <enemy id="enemy11_15" type="regularEnemy" x="310" y="230"/>
            <enemy id="enemy14_32" type="heavyEnemy" x="650" y="290"/>
            <enemy id="enemy15_1" type="heavyEnemy" x="30" y="310"/>
            <enemy id="enemy15_20" type="regularEnemy" x="410" y="310"/>
            <enemy id="enemy19_5" type="fastEnemy" x="110" y="390"/>
        </enemies>
        <staticObjects>
            <staticObject type="waterBlock" x="190" y="10"/>
            <staticObject type="waterBlock" x="210" y="10"/>
            <staticObject type="waterBlock" x="510" y="10"/>
            <staticObject type="waterBlock" x="530" y="10"/>
            <staticObject type="waterBlock" x="550" y="10"/>
            <staticObject type="waterBlock" x="190" y="30"/>
            <staticObject type="waterBlock" x="210" y="30"/>
            <staticObject type="waterBlock" x="510" y="30"/>
            <staticObject type="waterBlock" x="530" y="30"/>
            <staticObject type="waterBlock" x="550" y="30"/>
            <staticObject type="waterBlock" x="190" y="50"/>
            <staticObject type="waterBlock" x="210" y="50"/>
            <staticObject type="waterBlock" x="510" y="50"/>
            <staticObject type="waterBlock" x="530" y="50"/>
            <staticObject type="waterBlock" x="550" y="50"/>
            <staticObject type="waterBlock" x="10" y="70"/>
            <staticObject type="waterBlock" x="30" y="70"/>
            <staticObject type="waterBlock" x="50" y="70"/>
            <staticObject type="waterBlock" x="70" y="70"/>
            <staticObject type="waterBlock" x="90" y="70"/>
            <staticObject type="waterBlock" x="110" y="70"/>
            <staticObject type="waterBlock" x="190" y="70"/>
            <staticObject type="waterBlock" x="210" y="70"/>
            <staticObject type="waterBlock" x="350" y="70"/>
            <staticObject type="waterBlock" x="370" y="70"/>
            <staticObject type="waterBlock" x="390" y="70"/>
            <staticObject type="waterBlock" x="410" y="70"/>
            <staticObject type="waterBlock" x="430" y="70"/>
            <staticObject type="waterBlock" x="450" y="70"/>
            <staticObject type="waterBlock" x="470" y="70"/>
            <staticObject type="waterBlock" x="490" y="70"/>
            <staticObject type="waterBlock" x="510" y="70"/>
            <staticObject type="waterBlock" x="530" y="70"/>
            <staticObject type="waterBlock" x="550" y="70"/>
            <staticObject type="waterBlock" x="630" y="70"/>
            <staticObject type="waterBlock" x="650" y="70"/>
            <staticObject type="waterBlock" x="670" y="70"/>
            <staticObject type="waterBlock" x="690" y="70"/>
            <staticObject type="waterBlock" x="710" y="70"/>
            <staticObject type="waterBlock" x="730" y="70"/>
            <staticObject type="waterBlock" x="750" y="70"/>
            <staticObject type="waterBlock" x="770" y="70"/>
            <staticObject type="waterBlock" x="780" y="70"/>
            <staticObject type="waterBlock" x="10" y="90"/>
            <staticObject type="waterBlock" x="30" y="90"/>
            <staticObject type="waterBlock" x="50" y="90"/>
            <staticObject type="waterBlock" x="70" y="90"/>
            <staticObject type="waterBlock" x="90" y="90"/>
            <staticObject type="waterBlock" x="110" y="90"/>
            <staticObject type="waterBlock" x="190" y="90"/>
            <staticObject type="waterBlock" x="210" y="90"/>
            <staticObject type="waterBlock" x="350" y="90"/>
            <staticObject type="waterBlock" x="370" y="90"/>
            <staticObject type="waterBlock" x="390" y="90"/>
            <staticObject type="waterBlock" x="410" y="90"/>
            <staticObject type="waterBlock" x="430" y="90"/>
            <staticObject type="waterBlock" x="450" y="90"/>
            <staticObject type="waterBlock" x="470" y="90"/>
            <staticObject type="waterBlock" x="490" y="90"/>
            <staticObject type="waterBlock" x="510" y="90"/>
            <staticObject type="waterBlock" x="530" y="90"/>
            <staticObject type="waterBlock" x="550" y="90"/>
            <staticObject type="waterBlock" x="630" y="90"/>
            <staticObject type="waterBlock" x="650" y="90"/>
            <staticObject type="waterBlock" x="670" y="90"/>
            <staticObject type="waterBlock" x="690" y="90"/>
            <staticObject type="waterBlock" x="710" y="90"/>
            <staticObject type="waterBlock" x="730" y="90"/>
            <staticObject type="waterBlock" x="750" y="90"/>
            <staticObject type="waterBlock" x="770" y="90"/>
            <staticObject type="waterBlock" x="780" y="90"/>
            <staticObject type="forestBlock" x="10" y="110"/>
            <staticObject type="forestBlock" x="30" y="110"/>
            <staticObject type="forestBlock" x="50" y="110"/>
            <staticObject type="forestBlock" x="70" y="110"/>
            <staticObject type="forestBlock" x="90" y="110"/>
            <staticObject type="forestBlock" x="110" y="110"/>
            <staticObject type="brickBlock" x="130" y="110"/>
            <staticObject type="brickBlock" x="150" y="110"/>
            <staticObject type="brickBlock" x="170" y="110"/>
            <staticObject type="brickBlock" x="350" y="110"/>
            <staticObject type="brickBlock" x="370" y="110"/>
            <staticObject type="brickBlock" x="390" y="110"/>
            <staticObject type="waterBlock" x="530" y="110"/>
            <staticObject type="waterBlock" x="550" y="110"/>
            <staticObject type="waterBlock" x="630" y="110"/>
            <staticObject type="waterBlock" x="650" y="110"/>
            <staticObject type="waterBlock" x="670" y="110"/>
            <staticObject type="forestBlock" x="690" y="110"/>
            <staticObject type="forestBlock" x="710" y="110"/>
            <staticObject type="forestBlock" x="730" y="110"/>
            <staticObject type="waterBlock" x="750" y="110"/>
            <staticObject type="waterBlock" x="770" y="110"/>
            <staticObject type="waterBlock" x="780" y="110"/>
            <staticObject type="forestBlock" x="10" y="130"/>
            <staticObject type="forestBlock" x="30" y="130"/>
            <staticObject type="forestBlock" x="50" y="130"/>
            <staticObject type="forestBlock" x="70" y="130"/>
            <staticObject type="forestBlock" x="90" y="130"/>
            <staticObject type="forestBlock" x="110" y="130"/>
            <staticObject type="brickBlock" x="130" y="130"/>
            <staticObject type="brickBlock" x="150" y="130"/>
            <staticObject type="brickBlock" x="170" y="130"/>
            <staticObject type="brickBlock" x="350" y="130"/>
            <staticObject type="brickBlock" x="370" y="130"/>
            <staticObject type="brickBlock" x="390" y="130"/>
            <staticObject type="waterBlock" x="530" y="130"/>
            <staticObject type="waterBlock" x="550" y="130"/>
            <staticObject type="waterBlock" x="630" y="130"/>
            <staticObject type="waterBlock" x="650" y="130"/>
            <staticObject type="waterBlock" x="670" y="130"/>
            <staticObject type="forestBlock" x="690" y="130"/>
            <staticObject type="forestBlock" x="710" y="130"/>
            <staticObject type="forestBlock" x="730" y="130"/>
            <staticObject type="waterBlock" x="750" y="130"/>
            <staticObject type="waterBlock" x="770" y="130"/>
            <staticObject type="waterBlock" x="780" y="130"/>
            <staticObject type="forestBlock" x="10" y="150"/>
            <staticObject type="forestBlock" x="30" y="150"/>
            <staticObject type="forestBlock" x="50" y="150"/>
            <staticObject type="forestBlock" x="70" y="150"/>
            <staticObject type="forestBlock" x="90" y="150"/>
            <staticObject type="forestBlock" x="110" y="150"/>
            <staticObject type="brickBlock" x="130" y="150"/>
            <staticObject type="brickBlock" x="150" y="150"/>
            <staticObject type="brickBlock" x="170" y="150"/>
            <staticObject type="brickBlock" x="350" y="150"/>
            <staticObject type="brickBlock" x="370" y="150"/>
            <staticObject type="brickBlock" x="390" y="150"/>
            <staticObject type="waterBlock" x="530" y="150"/>
            <staticObject type="waterBlock" x="550" y="150"/>
            <staticObject type="waterBlock" x="630" y="150"/>
            <staticObject type="waterBlock" x="650" y="150"/>
            <staticObject type="waterBlock" x="670" y="150"/>
            <staticObject type="forestBlock" x="690" y="150"/>
            <staticObject type="forestBlock" x="710" y="150"/>
            <staticObject type="forestBlock" x="730" y="150"/>
            <staticObject type="waterBlock" x="750" y="150"/>
            <staticObject type="waterBlock" x="770" y="150"/>
            <staticObject type="waterBlock" x="780" y="150"/>
            <staticObject type="forestBlock" x="10" y="170"/>
            <staticObject type="forestBlock" x="30" y="170"/>
            <staticObject type="forestBlock" x="50" y="170"/>
            <staticObject type="waterBlock" x="70" y="170"/>
            <staticObject type="waterBlock" x="90" y="170"/>
            <staticObject type="waterBlock" x="110" y="170"/>
            <staticObject type="waterBlock" x="130" y="170"/>
            <staticObject type="waterBlock" x="150" y="170"/>
            <staticObject type="waterBlock" x="170" y="170"/>
            <staticObject type="waterBlock" x="190" y="170"/>
            <staticObject type="waterBlock" x="210" y="170"/>
            <staticObject type="waterBlock" x="230" y="170"/>
            <staticObject type="waterBlock" x="250" y="170"/>
            <staticObject type="waterBlock" x="270" y="170"/>
            <staticObject type="waterBlock" x="290" y="170"/>
            <staticObject type="waterBlock" x="310" y="170"/>
            <staticObject type="waterBlock" x="330" y="170"/>
            <staticObject type="steelBlock" x="410" y="170"/>
            <staticObject type="steelBlock" x="430" y="170"/>
            <staticObject type="steelBlock" x="450" y="170"/>
            <staticObject type="brickBlock" x="570" y="170"/>
            <staticObject type="brickBlock" x="590" y="170"/>
            <staticObject type="brickBlock" x="610" y="170"/>
            <staticObject type="forestBlock" x="630" y="170"/>
            <staticObject type="forestBlock" x="650" y="170"/>
            <staticObject type="forestBlock" x="670" y="170"/>
            <staticObject type="forestBlock" x="690" y="170"/>
            <staticObject type="forestBlock" x="710" y="170"/>
            <staticObject type="forestBlock" x="730" y="170"/>
            <staticObject type="forestBlock" x="750" y="170"/>
            <staticObject type="forestBlock" x="770" y="170"/>
            <staticObject type="forestBlock" x="780" y="170"/>
            <staticObject type="forestBlock" x="10" y="190"/>
            <staticObject type="forestBlock" x="30" y="190"/>
            <staticObject type="forestBlock" x="50" y="190"/>
            <staticObject type="waterBlock" x="70" y="190"/>
            <staticObject type="waterBlock" x="90" y="190"/>
            <staticObject type="waterBlock" x="110" y="190"/>
            <staticObject type="waterBlock" x="130" y="190"/>
            <staticObject type="waterBlock" x="150" y="190"/>
            <staticObject type="waterBlock" x="170" y="190"/>
            <staticObject type="waterBlock" x="190" y="190"/>
            <staticObject type="waterBlock" x="210" y="190"/>
            <staticObject type="waterBlock" x="230" y="190"/>
            <staticObject type="waterBlock" x="250" y="190"/>
            <staticObject type="waterBlock" x="270" y="190"/>
            <staticObject type="waterBlock" x="290" y="190"/>
            <staticObject type="waterBlock" x="310" y="190"/>
            <staticObject type="waterBlock" x="330" y="190"/>
            <staticObject type="steelBlock" x="410" y="190"/>
            <staticObject type="steelBlock" x="430" y="190"/>
            <staticObject type="steelBlock" x="450" y="190"/>
            <staticObject type="brickBlock" x="570" y="190"/>
            <staticObject type="brickBlock" x="590" y="190"/>
            <staticObject type="brickBlock" x="610" y="190"/>
            <staticObject type="forestBlock" x="630" y="190"/>
            <staticObject type="forestBlock" x="650" y="190"/>
            <staticObject type="forestBlock" x="670" y="190"/>
            <staticObject type="forestBlock" x="690" y="190"/>
            <staticObject type="forestBlock" x="710" y="190"/>
            <staticObject type="forestBlock" x="730" y="190"/>
            <staticObject type="forestBlock" x="750" y="190"/>
            <staticObject type="forestBlock" x="770" y="190"/>
            <staticObject type="forestBlock" x="780" y="190"/>
            <staticObject type="forestBlock" x="10" y="210"/>
            <staticObject type="forestBlock" x="30" y="210"/>
            <staticObject type="forestBlock" x="50" y="210"/>
            <staticObject type="forestBlock" x="70" y="210"/>
            <staticObject type="forestBlock" x="90" y="210"/>
            <staticObject type="forestBlock" x="110" y="210"/>
            <staticObject type="waterBlock" x="190" y="210"/>
            <staticObject type="waterBlock" x="210" y="210"/>
            <staticObject type="waterBlock" x="230" y="210"/>
            <staticObject type="waterBlock" x="250" y="210"/>
            <staticObject type="waterBlock" x="410" y="210"/>
            <staticObject type="waterBlock" x="430" y="210"/>
            <staticObject type="waterBlock" x="450" y="210"/>
            <staticObject type="waterBlock" x="530" y="210"/>
            <staticObject type="waterBlock" x="550" y="210"/>
            <staticObject type="waterBlock" x="570" y="210"/>
            <staticObject type="waterBlock" x="590" y="210"/>
            <staticObject type="waterBlock" x="610" y="210"/>
            <staticObject type="waterBlock" x="630" y="210"/>
            <staticObject type="waterBlock" x="650" y="210"/>
            <staticObject type="waterBlock" x="670" y="210"/>
            <staticObject type="waterBlock" x="690" y="210"/>
            <staticObject type="waterBlock" x="710" y="210"/>
            <staticObject type="waterBlock" x="730" y="210"/>
            <staticObject type="forestBlock" x="750" y="210"/>
            <staticObject type="forestBlock" x="770" y="210"/>
            <staticObject type="forestBlock" x="780" y="210"/>
            <staticObject type="forestBlock" x="10" y="230"/>
            <staticObject type="forestBlock" x="30" y="230"/>
            <staticObject type="forestBlock" x="50" y="230"/>
            <staticObject type="forestBlock" x="70" y="230"/>
            <staticObject type="forestBlock" x="90" y="230"/>
            <staticObject type="forestBlock" x="110" y="230"/>
            <staticObject type="waterBlock" x="190" y="230"/>
            <staticObject type="waterBlock" x="210" y="230"/>
            <staticObject type="waterBlock" x="230" y="230"/>
            <staticObject type="waterBlock" x="250" y="230"/>
            <staticObject type="waterBlock" x="410" y="230"/>
            <staticObject type="waterBlock" x="430" y="230"/>
            <staticObject type="waterBlock" x="450" y="230"/>
            <staticObject type="waterBlock" x="530" y="230"/>
            <staticObject type="waterBlock" x="550" y="230"/>
            <staticObject type="waterBlock" x="570" y="230"/>
            <staticObject type="waterBlock" x="590" y="230"/>
            <staticObject type="waterBlock" x="610" y="230"/>
            <staticObject type="waterBlock" x="630" y="230"/>
            <staticObject type="waterBlock" x="650" y="230"/>
            <staticObject type="waterBlock" x="670" y="230"/>
            <staticObject type="waterBlock" x="690" y="230"/>
            <staticObject type="waterBlock" x="710" y="230"/>
            <staticObject type="waterBlock" x="730" y="230"/>
            <staticObject type="forestBlock" x="750" y="230"/>
            <staticObject type="forestBlock" x="770" y="230"/>
            <staticObject type="forestBlock" x="780" y="230"/>
            <staticObject type="waterBlock" x="10" y="250"/>
            <staticObject type="waterBlock" x="30" y="250"/>
            <staticObject type="waterBlock" x="50" y="250"/>
            <staticObject type="waterBlock" x="70" y="250"/>
            <staticObject type="waterBlock" x="90" y="250"/>
            <staticObject type="waterBlock" x="110" y="250"/>
            <staticObject type="waterBlock" x="130" y="250"/>
            <staticObject type="waterBlock" x="190" y="250"/>
            <staticObject type="waterBlock" x="210" y="250"/>
            <staticObject type="waterBlock" x="230" y="250"/>
            <staticObject type="waterBlock" x="250" y="250"/>
            <staticObject type="waterBlock" x="350" y="250"/>
            <staticObject type="waterBlock" x="370" y="250"/>
            <staticObject type="waterBlock" x="390" y="250"/>
            <staticObject type="waterBlock" x="410" y="250"/>
            <staticObject type="waterBlock" x="430" y="250"/>
            <staticObject type="waterBlock" x="450" y="250"/>
            <staticObject type="waterBlock" x="530" y="250"/>
            <staticObject type="waterBlock" x="550" y="250"/>
            <staticObject type="waterBlock" x="570" y="250"/>
            <staticObject type="waterBlock" x="590" y="250"/>
            <staticObject type="waterBlock" x="610" y="250"/>
            <staticObject type="waterBlock" x="630" y="250"/>
            <staticObject type="waterBlock" x="650" y="250"/>
            <staticObject type="waterBlock" x="670" y="250"/>
            <staticObject type="waterBlock" x="690" y="250"/>
            <staticObject type="waterBlock" x="710" y="250"/>
            <staticObject type="waterBlock" x="730" y="250"/>
            <staticObject type="forestBlock" x="750" y="250"/>
            <staticObject type="forestBlock" x="770" y="250"/>
            <staticObject type="forestBlock" x="780" y="250"/>
            <staticObject type="waterBlock" x="10" y="270"/>
            <staticObject type="waterBlock" x="30" y="270"/>
            <staticObject type="waterBlock" x="50" y="270"/>
            <staticObject type="waterBlock" x="70" y="270"/>
            <staticObject type="waterBlock" x="90" y="270"/>
            <staticObject type="waterBlock" x="110" y="270"/>
            <staticObject type="waterBlock" x="130" y="270"/>
            <staticObject type="waterBlock" x="190" y="270"/>
            <staticObject type="waterBlock" x="210" y="270"/>
            <staticObject type="waterBlock" x="230" y="270"/>
            <staticObject type="waterBlock" x="250" y="270"/>
            <staticObject type="waterBlock" x="350" y="270"/>
            <staticObject type="waterBlock" x="370" y="270"/>
            <staticObject type="waterBlock" x="390" y="270"/>
            <staticObject type="waterBlock" x="410" y="270"/>
            <staticObject type="waterBlock" x="430" y="270"/>
            <staticObject type="waterBlock" x="450" y="270"/>
            <staticObject type="waterBlock" x="590" y="270"/>
            <staticObject type="waterBlock" x="610" y="270"/>
            <staticObject type="forestBlock" x="780" y="270"/>
            <staticObject type="brickBlock" x="150" y="290"/>
            <staticObject type="brickBlock" x="170" y="290"/>
            <staticObject type="forestBlock" x="190" y="290"/>
            <staticObject type="forestBlock" x="210" y="290"/>
            <staticObject type="forestBlock" x="230" y="290"/>
            <staticObject type="forestBlock" x="250" y="290"/>
            <staticObject type="forestBlock" x="270" y="290"/>
            <staticObject type="forestBlock" x="290" y="290"/>
            <staticObject type="forestBlock" x="310" y="290"/>
            <staticObject type="forestBlock" x="330" y="290"/>
            <staticObject type="brickBlock" x="350" y="290"/>
            <staticObject type="brickBlock" x="370" y="290"/>
            <staticObject type="waterBlock" x="590" y="290"/>
            <staticObject type="waterBlock" x="610" y="290"/>
            <staticObject type="brickBlock" x="150" y="310"/>
            <staticObject type="brickBlock" x="170" y="310"/>
            <staticObject type="forestBlock" x="190" y="310"/>
            <staticObject type="forestBlock" x="210" y="310"/>
            <staticObject type="forestBlock" x="230" y="310"/>
            <staticObject type="forestBlock" x="250" y="310"/>
            <staticObject type="forestBlock" x="270" y="310"/>
            <staticObject type="forestBlock" x="290" y="310"/>
            <staticObject type="forestBlock" x="310" y="310"/>
            <staticObject type="forestBlock" x="330" y="310"/>
            <staticObject type="brickBlock" x="350" y="310"/>
            <staticObject type="brickBlock" x="370" y="310"/>
            <staticObject type="waterBlock" x="590" y="310"/>
            <staticObject type="waterBlock" x="610" y="310"/>
            <staticObject type="waterBlock" x="780" y="310"/>
            <staticObject type="waterBlock" x="70" y="330"/>
            <staticObject type="waterBlock" x="90" y="330"/>
            <staticObject type="waterBlock" x="110" y="330"/>
            <staticObject type="waterBlock" x="130" y="330"/>
            <staticObject type="waterBlock" x="150" y="330"/>
            <staticObject type="waterBlock" x="170" y="330"/>
            <staticObject type="forestBlock" x="190" y="330"/>
            <staticObject type="forestBlock" x="210" y="330"/>
            <staticObject type="forestBlock" x="230" y="330"/>
            <staticObject type="forestBlock" x="250" y="330"/>
            <staticObject type="forestBlock" x="270" y="330"/>
            <staticObject type="forestBlock" x="290" y="330"/>
            <staticObject type="forestBlock" x="310" y="330"/>
            <staticObject type="forestBlock" x="330" y="330"/>
            <staticObject type="waterBlock" x="350" y="330"/>
            <staticObject type="waterBlock" x="370" y="330"/>
            <staticObject type="waterBlock" x="390" y="330"/>
            <staticObject type="waterBlock" x="410" y="330"/>
            <staticObject type="waterBlock" x="430" y="330"/>
            <staticObject type="waterBlock" x="450" y="330"/>
            <staticObject type="waterBlock" x="590" y="330"/>
            <staticObject type="waterBlock" x="610" y="330"/>
            <staticObject type="waterBlock" x="780" y="330"/>
            <staticObject type="waterBlock" x="70" y="350"/>
            <staticObject type="waterBlock" x="90" y="350"/>
            <staticObject type="waterBlock" x="110" y="350"/>
            <staticObject type="waterBlock" x="130" y="350"/>
            <staticObject type="waterBlock" x="150" y="350"/>
            <staticObject type="waterBlock" x="170" y="350"/>
            <staticObject type="forestBlock" x="190" y="350"/>
            <staticObject type="forestBlock" x="210" y="350"/>
            <staticObject type="forestBlock" x="230" y="350"/>
            <staticObject type="forestBlock" x="250" y="350"/>
            <staticObject type="forestBlock" x="270" y="350"/>
            <staticObject type="forestBlock" x="290" y="350"/>
            <staticObject type="forestBlock" x="310" y="350"/>
            <staticObject type="forestBlock" x="330" y="350"/>
            <staticObject type="waterBlock" x="350" y="350"/>
            <staticObject type="waterBlock" x="370" y="350"/>
            <staticObject type="waterBlock" x="390" y="350"/>
            <staticObject type="waterBlock" x="410" y="350"/>
            <staticObject type="waterBlock" x="430" y="350"/>
            <staticObject type="waterBlock" x="450" y="350"/>
            <staticObject type="waterBlock" x="590" y="350"/>
            <staticObject type="waterBlock" x="610" y="350"/>
            <staticObject type="waterBlock" x="780" y="350"/>
            <staticObject type="brickBlock" x="10" y="370"/>
            <staticObject type="brickBlock" x="30" y="370"/>
            <staticObject type="brickBlock" x="50" y="370"/>
            <staticObject type="brickBlock" x="190" y="370"/>
            <staticObject type="brickBlock" x="210" y="370"/>
            <staticObject type="brickBlock" x="230" y="370"/>
            <staticObject type="brickBlock" x="250" y="370"/>
            <staticObject type="forestBlock" x="270" y="370"/>
            <staticObject type="forestBlock" x="290" y="370"/>
            <staticObject type="forestBlock" x="310" y="370"/>
            <staticObject type="forestBlock" x="330" y="370"/>
            <staticObject type="waterBlock" x="350" y="370"/>
            <staticObject type="waterBlock" x="370" y="370"/>
            <staticObject type="waterBlock" x="590" y="370"/>
            <staticObject type="waterBlock" x="610" y="370"/>
            <staticObject type="waterBlock" x="780" y="370"/>
            <staticObject type="brickBlock" x="10" y="390"/>
            <staticObject type="brickBlock" x="30" y="390"/>
            <staticObject type="brickBlock" x="50" y="390"/>
            <staticObject type="brickBlock" x="190" y="390"/>
            <staticObject type="brickBlock" x="210" y="390"/>
            <staticObject type="brickBlock" x="230" y="390"/>
            <staticObject type="brickBlock" x="250" y="390"/>
            <staticObject type="forestBlock" x="270" y="390"/>
            <staticObject type="forestBlock" x="290" y="390"/>
            <staticObject type="forestBlock" x="310" y="390"/>
            <staticObject type="forestBlock" x="330" y="390"/>
            <staticObject type="waterBlock" x="350" y="390"/>
            <staticObject type="waterBlock" x="370" y="390"/>
            <staticObject type="waterBlock" x="590" y="390"/>
            <staticObject type="waterBlock" x="610" y="390"/>
            <staticObject type="waterBlock" x="780" y="390"/>
            <staticObject type="brickBlock" x="10" y="410"/>
            <staticObject type="brickBlock" x="30" y="410"/>
            <staticObject type="brickBlock" x="50" y="410"/>
            <staticObject type="brickBlock" x="190" y="410"/>
            <staticObject type="brickBlock" x="210" y="410"/>
            <staticObject type="brickBlock" x="230" y="410"/>
            <staticObject type="brickBlock" x="250" y="410"/>
            <staticObject type="forestBlock" x="270" y="410"/>
            <staticObject type="forestBlock" x="290" y="410"/>
            <staticObject type="forestBlock" x="310" y="410"/>
            <staticObject type="forestBlock" x="330" y="410"/>
            <staticObject type="waterBlock" x="350" y="410"/>
            <staticObject type="waterBlock" x="370" y="410"/>
            <staticObject type="forestBlock" x="590" y="410"/>
            <staticObject type="forestBlock" x="610" y="410"/>
            <staticObject type="brickBlock" x="630" y="410"/>
            <staticObject type="brickBlock" x="650" y="410"/>
            <staticObject type="waterBlock" x="780" y="410"/>
            <staticObject type="waterBlock" x="10" y="430"/>
            <staticObject type="waterBlock" x="30" y="430"/>
            <staticObject type="waterBlock" x="50" y="430"/>
            <staticObject type="waterBlock" x="70" y="430"/>
            <staticObject type="waterBlock" x="90" y="430"/>
            <staticObject type="waterBlock" x="110" y="430"/>
            <staticObject type="waterBlock" x="190" y="430"/>
            <staticObject type="waterBlock" x="210" y="430"/>
            <staticObject type="waterBlock" x="230" y="430"/>
            <staticObject type="waterBlock" x="250" y="430"/>
            <staticObject type="forestBlock" x="270" y="430"/>
            <staticObject type="forestBlock" x="290" y="430"/>
            <staticObject type="waterBlock" x="310" y="430"/>
            <staticObject type="waterBlock" x="330" y="430"/>
            <staticObject type="waterBlock" x="350" y="430"/>
            <staticObject type="waterBlock" x="370" y="430"/>
            <staticObject type="forestBlock" x="590" y="430"/>
            <staticObject type="forestBlock" x="610" y="430"/>
            <staticObject type="brickBlock" x="630" y="430"/>
            <staticObject type="brickBlock" x="650" y="430"/>
            <staticObject type="waterBlock" x="780" y="430"/>
            <staticObject type="waterBlock" x="10" y="450"/>
            <staticObject type="waterBlock" x="30" y="450"/>
            <staticObject type="waterBlock" x="50" y="450"/>
            <staticObject type="waterBlock" x="70" y="450"/>
            <staticObject type="waterBlock" x="90" y="450"/>
            <staticObject type="waterBlock" x="110" y="450"/>
            <staticObject type="waterBlock" x="190" y="450"/>
            <staticObject type="waterBlock" x="210" y="450"/>
            <staticObject type="waterBlock" x="230" y="450"/>
            <staticObject type="waterBlock" x="250" y="450"/>
            <staticObject type="forestBlock" x="270" y="450"/>
            <staticObject type="forestBlock" x="290" y="450"/>
            <staticObject type="waterBlock" x="310" y="450"/>
            <staticObject type="waterBlock" x="330" y="450"/>
            <staticObject type="waterBlock" x="350" y="450"/>
            <staticObject type="waterBlock" x="370" y="450"/>
            <staticObject type="forestBlock" x="550" y="450"/>
            <staticObject type="forestBlock" x="570" y="450"/>
            <staticObject type="forestBlock" x="590" y="450"/>
            <staticObject type="forestBlock" x="610" y="450"/>
            <staticObject type="waterBlock" x="630" y="450"/>
            <staticObject type="waterBlock" x="650" y="450"/>
            <staticObject type="waterBlock" x="780" y="450"/>
            <staticObject type="forestBlock" x="230" y="470"/>
            <staticObject type="forestBlock" x="250" y="470"/>
            <staticObject type="forestBlock" x="270" y="470"/>
            <staticObject type="forestBlock" x="290" y="470"/>
            <staticObject type="forestBlock" x="550" y="470"/>
            <staticObject type="forestBlock" x="570" y="470"/>
            <staticObject type="forestBlock" x="590" y="470"/>
            <staticObject type="forestBlock" x="610" y="470"/>
            <staticObject type="waterBlock" x="630" y="470"/>
            <staticObject type="waterBlock" x="650" y="470"/>
            <staticObject type="waterBlock" x="770" y="470"/>
            <staticObject type="waterBlock" x="780" y="470"/>
            <staticObject type="forestBlock" x="230" y="490"/>
            <staticObject type="forestBlock" x="250" y="490"/>
            <staticObject type="forestBlock" x="270" y="490"/>
            <staticObject type="forestBlock" x="290" y="490"/>
            <staticObject type="waterBlock" x="550" y="490"/>
            <staticObject type="waterBlock" x="570" y="490"/>
            <staticObject type="waterBlock" x="590" y="490"/>
            <staticObject type="waterBlock" x="610" y="490"/>
            <staticObject type="waterBlock" x="630" y="490"/>
            <staticObject type="waterBlock" x="650" y="490"/>
            <staticObject type="waterBlock" x="750" y="490"/>
            <staticObject type="waterBlock" x="770" y="490"/>
            <staticObject type="waterBlock" x="780" y="490"/>
            <staticObject type="waterBlock" x="110" y="510"/>
            <staticObject type="waterBlock" x="130" y="510"/>
            <staticObject type="waterBlock" x="150" y="510"/>
            <staticObject type="waterBlock" x="170" y="510"/>
            <staticObject type="waterBlock" x="190" y="510"/>
            <staticObject type="waterBlock" x="210" y="510"/>
            <staticObject type="forestBlock" x="230" y="510"/>
            <staticObject type="forestBlock" x="250" y="510"/>
            <staticObject type="waterBlock" x="550" y="510"/>
            <staticObject type="waterBlock" x="570" y="510"/>
            <staticObject type="waterBlock" x="590" y="510"/>
            <staticObject type="waterBlock" x="610" y="510"/>
            <staticObject type="waterBlock" x="630" y="510"/>
            <staticObject type="waterBlock" x="650" y="510"/>
            <staticObject type="waterBlock" x="750" y="510"/>
            <staticObject type="waterBlock" x="770" y="510"/>
            <staticObject type="waterBlock" x="780" y="510"/>
            <staticObject type="waterBlock" x="110" y="530"/>
            <staticObject type="waterBlock" x="130" y="530"/>
            <staticObject type="waterBlock" x="150" y="530"/>
            <staticObject type="waterBlock" x="170" y="530"/>
            <staticObject type="waterBlock" x="190" y="530"/>
            <staticObject type="waterBlock" x="210" y="530"/>
            <staticObject type="forestBlock" x="230" y="530"/>
            <staticObject type="forestBlock" x="250" y="530"/>
            <staticObject type="brickBlock" x="390" y="530"/>
            <staticObject type="brickBlock" x="410" y="530"/>
            <staticObject type="brickBlock" x="430" y="530"/>
            <staticObject type="brickBlock" x="450" y="530"/>
            <staticObject type="brickBlock" x="470" y="530"/>
            <staticObject type="waterBlock" x="110" y="550"/>
            <staticObject type="waterBlock" x="130" y="550"/>
            <staticObject type="brickBlock" x="390" y="550"/>
            <staticObject type="brickBlock" x="470" y="550"/>
            <staticObject type="waterBlock" x="110" y="570"/>
            <staticObject type="waterBlock" x="130" y="570"/>
            <staticObject type="brickBlock" x="390" y="570"/>
            <staticObject type="baseBlock" x="430" y="570"/>
            <staticObject type="brickBlock" x="470" y="570"/>
            <staticObject type="waterBlock" x="110" y="580"/>
            <staticObject type="waterBlock" x="130" y="580"/>
            <staticObject type="brickBlock" x="390" y="580"/>
            <staticObject type="brickBlock" x="470" y="580"/>
        </staticObjects>
    </level>
</levelConfig>
